{
  "forge_marker": 1,
  "defaults": {
    "textures": {
		"down": "contenttweaker:blocks/logs/amaranth_log_top",
		"up": "contenttweaker:blocks/logs/amaranth_log_top",
		"north": "contenttweaker:blocks/logs/amaranth_log_debarked_side",
		"east": "contenttweaker:blocks/logs/amaranth_log_debarked_side",
		"south": "contenttweaker:blocks/logs/amaranth_log_debarked_side",
		"west": "contenttweaker:blocks/logs/amaranth_log_debarked_side"
    },
    "model": "cube_all",
    "uvlock": true,
    "transform": "forge:default-block"
  },
  "variants": {
    "normal": [{}],
    "inventory": [{}]
  }
}